{"frames": {

"Death_Base.png":
{
	"frame": {"x":0,"y":0,"w":3850,"h":1400},
	"rotated": false,
	"trimmed": false,
	"spriteSourceSize": {"x":0,"y":0,"w":3850,"h":1400},
	"sourceSize": {"w":3850,"h":1400}
},
"Death_Blue.png":
{
	"frame": {"x":0,"y":1400,"w":3850,"h":1400},
	"rotated": false,
	"trimmed": false,
	"spriteSourceSize": {"x":0,"y":0,"w":3850,"h":1400},
	"sourceSize": {"w":3850,"h":1400}
}},
"meta": {
	"app": "https://www.codeandweb.com/texturepacker",
	"version": "1.0",
	"image": "Mochi 2.png",
	"format": "RGBA8888",
	"size": {"w":3850,"h":2800},
	"scale": "1",
	"smartupdate": "$TexturePacker:SmartUpdate:7bc1c20f514941d93e94281517108bd3:68b23771bbca06875921995b385851e0:1c891a9953c52954163925dba9dd3e9e$"
}
}
